cmsbooklet/__init__.py
cmsbooklet/cmsbooklet.py
cmsbooklet/templates/__init__.py
cmsbooklet/templates/cms-contest/contest.tpl
cmsbooklet/templates/cms-contest/defaults.yaml
cmsbooklet/templates/cms-contest/problem.tpl
cmsbooklet/templates/cms-contest/data/cms-contest.cls
cmsbooklet/templates/cms-contest/data/locale/english.tex
cmsbooklet/templates/cms-contest/data/locale/italian.tex
cmsbooklet-1.5.data/scripts/mktesto
cmsbooklet-1.5.dist-info/LICENSE
cmsbooklet-1.5.dist-info/METADATA
cmsbooklet-1.5.dist-info/WHEEL
cmsbooklet-1.5.dist-info/entry_points.txt
cmsbooklet-1.5.dist-info/top_level.txt
cmsbooklet-1.5.dist-info/RECORD
