Metadata-Version: 2.1
Name: cmsbooklet
Version: 1.5
Summary: cmsbooklet: problem statement processor for CMS (Contest Management System)
Home-page: UNKNOWN
Author: Gabriele Farina
Author-email: gabr.farina@gmail.com
License: UNKNOWN
Platform: UNKNOWN
Requires-Dist: pyyaml
Requires-Dist: jinja2
